_turboloader.cpython-313-darwin.so
turboloader/__init__.py
turboloader-2.23.0.dist-info/licenses/AUTHORS.md
turboloader-2.23.0.dist-info/licenses/LICENSE
turboloader-2.23.0.dist-info/METADATA
turboloader-2.23.0.dist-info/WHEEL
turboloader-2.23.0.dist-info/top_level.txt
turboloader-2.23.0.dist-info/RECORD
