Metadata-Version: 2.4
Name: turboloader
Version: 2.23.0
Summary: Production-ready ML data loading library with distributed training support, SIMD-accelerated transforms, pipe operator composition, HDF5/TFRecord/Zarr support, and GPU transforms. Built with C++17 for maximum performance.
Author: TurboLoader Contributors
Author-email: Arnav Jain <arnav@example.com>
Maintainer-email: Arnav Jain <arnav@example.com>
License: MIT
Project-URL: Homepage, https://github.com/ALJainProjects/TurboLoader
Project-URL: Documentation, https://github.com/ALJainProjects/TurboLoader/blob/main/README.md
Project-URL: Repository, https://github.com/ALJainProjects/TurboLoader
Project-URL: Bug Tracker, https://github.com/ALJainProjects/TurboLoader/issues
Project-URL: Changelog, https://github.com/ALJainProjects/TurboLoader/blob/main/CHANGELOG.md
Project-URL: Discussions, https://github.com/ALJainProjects/TurboLoader/discussions
Keywords: machine-learning,deep-learning,data-loading,pytorch,performance,simd,imagenet,computer-vision
Classifier: Development Status :: 5 - Production/Stable
Classifier: Intended Audience :: Developers
Classifier: Intended Audience :: Science/Research
Classifier: Operating System :: POSIX :: Linux
Classifier: Operating System :: MacOS :: MacOS X
Classifier: Programming Language :: C++
Classifier: Programming Language :: Python :: 3
Classifier: Programming Language :: Python :: 3.10
Classifier: Programming Language :: Python :: 3.11
Classifier: Programming Language :: Python :: 3.12
Classifier: Topic :: Scientific/Engineering :: Artificial Intelligence
Classifier: Topic :: Software Development :: Libraries :: Python Modules
Requires-Python: >=3.10
License-File: LICENSE
License-File: AUTHORS.md
Requires-Dist: numpy>=1.19.0
Requires-Dist: torch>=1.8.0
Provides-Extra: dev
Requires-Dist: pytest>=6.0; extra == "dev"
Requires-Dist: black>=21.0; extra == "dev"
Requires-Dist: flake8>=3.9; extra == "dev"
Requires-Dist: mypy>=0.900; extra == "dev"
Requires-Dist: build>=0.7.0; extra == "dev"
Requires-Dist: twine>=3.4.0; extra == "dev"
Provides-Extra: benchmarks
Requires-Dist: Pillow>=8.0.0; extra == "benchmarks"
Requires-Dist: tqdm>=4.60.0; extra == "benchmarks"
Requires-Dist: matplotlib>=3.3.0; extra == "benchmarks"
Requires-Dist: psutil>=5.8.0; extra == "benchmarks"
Provides-Extra: all
Requires-Dist: turboloader[benchmarks,dev]; extra == "all"
Dynamic: author
Dynamic: license-file
Dynamic: requires-python
